{
  "_fv": 39,
  "_type": "overlay",
  "definition": {
    "priority": "NORMAL",
    "components": [
      {
        "type": "image",
        "data": {
          "image": "xpfont.png",
          "use1Xscale": true,
          "x": 416,
          "y": -11
        }
      },
      {
        "type": "label",
        "data": {
          "name": "label_varintegerxpnumber_xp",
          "text": {
            "fixedValue": "+<VAR:integer:xpnumber> XP"
          },
          "color": {
            "value": -16777216,
            "falpha": 0.0
          },
          "x": 429,
          "y": 19
        }
      },
      {
        "type": "label",
        "data": {
          "name": "label_varxptype",
          "text": {
            "fixedValue": "<VAR:xptype>"
          },
          "color": {
            "value": -16777216,
            "falpha": 0.0
          },
          "x": 425,
          "y": -3
        }
      },
      {
        "type": "image",
        "data": {
          "image": "wooden_pick.png",
          "use1Xscale": false,
          "displayCondition": {
            "name": "MiningOn"
          },
          "x": 494,
          "y": -4
        }
      },
      {
        "type": "image",
        "data": {
          "image": "fishing_rod.png",
          "use1Xscale": false,
          "displayCondition": {
            "name": "FishingOn"
          },
          "x": 494,
          "y": -4
        }
      },
      {
        "type": "image",
        "data": {
          "image": "wooden_sword.png",
          "use1Xscale": false,
          "displayCondition": {
            "name": "CombatOn"
          },
          "x": 494,
          "y": -4
        }
      },
      {
        "type": "image",
        "data": {
          "image": "wood_axe.png",
          "use1Xscale": false,
          "displayCondition": {
            "name": "ForagingOn"
          },
          "x": 494,
          "y": -4
        }
      },
      {
        "type": "image",
        "data": {
          "image": "wood_hoe.png",
          "use1Xscale": false,
          "displayCondition": {
            "name": "FarmingOn"
          },
          "x": 494,
          "y": -4
        }
      }
    ],
    "baseTexture": "",
    "overlayTarget": "Ingame",
    "displayCondition": {
      "name": "XpgainedOn"
    },
    "gridSettings": {
      "sx": 18,
      "sy": 18,
      "ox": 11,
      "oy": 15,
      "snapOnGrid": false
    }
  }
}